{
  "source": "twitchdownloader",
  "twitchVodId": "2714647660",
  "generatedAt": "2026-03-06T01:07:14.902Z",
  "comments": [
    {
      "id": "20830594-dd56-4114-8a4a-99ccf8708f8a",
      "created_at": "2026-03-05T20:20:50.681Z",
      "content_offset_seconds": 1206,
      "display_name": "softu1",
      "user_badges": [
        {
          "_id": "broadcaster",
          "version": "1"
        },
        {
          "_id": "subscriber",
          "version": "0"
        },
        {
          "_id": "glitchcon2020",
          "version": "1"
        }
      ],
      "user_color": "#27FFD7",
      "message": [
        {
          "text": "RainbowPls",
          "emoticon": null
        }
      ]
    },
    {
      "id": "5422e6e0-5540-4cf0-84d4-5fd1ef9665c9",
      "created_at": "2026-03-05T21:56:49.776Z",
      "content_offset_seconds": 6966,
      "display_name": "MiCkEyRoTtEn",
      "user_badges": [
        {
          "_id": "vip",
          "version": "1"
        },
        {
          "_id": "founder",
          "version": "0"
        },
        {
          "_id": "share-the-love",
          "version": "1"
        }
      ],
      "user_color": "#9ACD32",
      "message": [
        {
          "text": "hiii",
          "emoticon": null
        }
      ]
    },
    {
      "id": "0572a2f7-e739-4ade-928c-c9a1c9d023ba",
      "created_at": "2026-03-05T21:56:57.579Z",
      "content_offset_seconds": 6973,
      "display_name": "MiCkEyRoTtEn",
      "user_badges": [
        {
          "_id": "vip",
          "version": "1"
        },
        {
          "_id": "founder",
          "version": "0"
        },
        {
          "_id": "share-the-love",
          "version": "1"
        }
      ],
      "user_color": "#9ACD32",
      "message": [
        {
          "text": "it's mee",
          "emoticon": null
        }
      ]
    },
    {
      "id": "364b27f2-9dc4-4cad-8cbc-e6a4e852aebc",
      "created_at": "2026-03-05T21:57:08.507Z",
      "content_offset_seconds": 6984,
      "display_name": "MiCkEyRoTtEn",
      "user_badges": [
        {
          "_id": "vip",
          "version": "1"
        },
        {
          "_id": "founder",
          "version": "0"
        },
        {
          "_id": "share-the-love",
          "version": "1"
        }
      ],
      "user_color": "#9ACD32",
      "message": [
        {
          "text": "The stalker",
          "emoticon": null
        }
      ]
    },
    {
      "id": "fb0f6d6e-3976-4513-bfaa-921bec00cbdd",
      "created_at": "2026-03-05T21:57:25.313Z",
      "content_offset_seconds": 7001,
      "display_name": "MiCkEyRoTtEn",
      "user_badges": [
        {
          "_id": "vip",
          "version": "1"
        },
        {
          "_id": "founder",
          "version": "0"
        },
        {
          "_id": "share-the-love",
          "version": "1"
        }
      ],
      "user_color": "#9ACD32",
      "message": [
        {
          "text": "looking niiice",
          "emoticon": null
        }
      ]
    },
    {
      "id": "10db6652-8d41-4f6f-8065-bf16cd21908f",
      "created_at": "2026-03-05T21:57:45.937Z",
      "content_offset_seconds": 7022,
      "display_name": "MiCkEyRoTtEn",
      "user_badges": [
        {
          "_id": "vip",
          "version": "1"
        },
        {
          "_id": "founder",
          "version": "0"
        },
        {
          "_id": "share-the-love",
          "version": "1"
        }
      ],
      "user_color": "#9ACD32",
      "message": [
        {
          "text": "But yeah just popped in to say I'm Hella dead",
          "emoticon": null
        }
      ]
    },
    {
      "id": "f0b3f03b-5708-4809-b6f4-dc14d8ef476b",
      "created_at": "2026-03-05T21:58:01.268Z",
      "content_offset_seconds": 7037,
      "display_name": "MiCkEyRoTtEn",
      "user_badges": [
        {
          "_id": "vip",
          "version": "1"
        },
        {
          "_id": "founder",
          "version": "0"
        },
        {
          "_id": "share-the-love",
          "version": "1"
        }
      ],
      "user_color": "#9ACD32",
      "message": [
        {
          "text": "and probably need to sleep Dx",
          "emoticon": null
        }
      ]
    },
    {
      "id": "c927f75f-e115-4da7-ad24-c51b2efe6698",
      "created_at": "2026-03-05T21:58:33.237Z",
      "content_offset_seconds": 7069,
      "display_name": "MiCkEyRoTtEn",
      "user_badges": [
        {
          "_id": "vip",
          "version": "1"
        },
        {
          "_id": "founder",
          "version": "0"
        },
        {
          "_id": "share-the-love",
          "version": "1"
        }
      ],
      "user_color": "#9ACD32",
      "message": [
        {
          "text": "but gonna again lurk here",
          "emoticon": null
        }
      ]
    },
    {
      "id": "352701e2-53f6-45db-b738-08fa6714740c",
      "created_at": "2026-03-05T21:59:29.942Z",
      "content_offset_seconds": 7126,
      "display_name": "MiCkEyRoTtEn",
      "user_badges": [
        {
          "_id": "vip",
          "version": "1"
        },
        {
          "_id": "founder",
          "version": "0"
        },
        {
          "_id": "share-the-love",
          "version": "1"
        }
      ],
      "user_color": "#9ACD32",
      "message": [
        {
          "text": "and the music's pretty loud compared to your voice rn btw",
          "emoticon": null
        }
      ]
    },
    {
      "id": "ebf9f572-6347-4604-be23-c4b41e4a103a",
      "created_at": "2026-03-05T22:00:07.597Z",
      "content_offset_seconds": 7163,
      "display_name": "MiCkEyRoTtEn",
      "user_badges": [
        {
          "_id": "vip",
          "version": "1"
        },
        {
          "_id": "founder",
          "version": "0"
        },
        {
          "_id": "share-the-love",
          "version": "1"
        }
      ],
      "user_color": "#9ACD32",
      "message": [
        {
          "text": "better yeah",
          "emoticon": null
        }
      ]
    },
    {
      "id": "456d0475-60c4-4e61-84fe-39057c88278a",
      "created_at": "2026-03-05T22:00:58.615Z",
      "content_offset_seconds": 7214,
      "display_name": "MiCkEyRoTtEn",
      "user_badges": [
        {
          "_id": "vip",
          "version": "1"
        },
        {
          "_id": "founder",
          "version": "0"
        },
        {
          "_id": "share-the-love",
          "version": "1"
        }
      ],
      "user_color": "#9ACD32",
      "message": [
        {
          "text": "heckin cute",
          "emoticon": null
        }
      ]
    },
    {
      "id": "c7349f5a-eceb-49c9-b85b-338caf9a0b3a",
      "created_at": "2026-03-05T22:02:24.065Z",
      "content_offset_seconds": 7300,
      "display_name": "Fossabot",
      "user_badges": [
        {
          "_id": "moderator",
          "version": "1"
        },
        {
          "_id": "bot-badge",
          "version": "1"
        }
      ],
      "user_color": "#1976D2",
      "message": [
        {
          "text": "Explosion nya Explosion",
          "emoticon": null
        }
      ]
    },
    {
      "id": "2e5b4c2a-176a-4e90-92ed-bdca35ad66e5",
      "created_at": "2026-03-05T22:03:37.355Z",
      "content_offset_seconds": 7373,
      "display_name": "MiCkEyRoTtEn",
      "user_badges": [
        {
          "_id": "vip",
          "version": "1"
        },
        {
          "_id": "founder",
          "version": "0"
        },
        {
          "_id": "share-the-love",
          "version": "1"
        }
      ],
      "user_color": "#9ACD32",
      "message": [
        {
          "text": "sounds good but damn this weak flesh of mine",
          "emoticon": null
        }
      ]
    },
    {
      "id": "efb6ed57-7026-4ede-ad22-f36707ff7238",
      "created_at": "2026-03-05T22:04:03.562Z",
      "content_offset_seconds": 7399,
      "display_name": "MiCkEyRoTtEn",
      "user_badges": [
        {
          "_id": "vip",
          "version": "1"
        },
        {
          "_id": "founder",
          "version": "0"
        },
        {
          "_id": "share-the-love",
          "version": "1"
        }
      ],
      "user_color": "#9ACD32",
      "message": [
        {
          "text": "ah yeah it did",
          "emoticon": null
        }
      ]
    },
    {
      "id": "4eab7829-5280-4411-a08e-af01f8ac07c5",
      "created_at": "2026-03-05T22:04:08.388Z",
      "content_offset_seconds": 7404,
      "display_name": "MiCkEyRoTtEn",
      "user_badges": [
        {
          "_id": "vip",
          "version": "1"
        },
        {
          "_id": "founder",
          "version": "0"
        },
        {
          "_id": "share-the-love",
          "version": "1"
        }
      ],
      "user_color": "#9ACD32",
      "message": [
        {
          "text": "passed",
          "emoticon": null
        }
      ]
    },
    {
      "id": "c7346ed8-dce8-4cf5-8f31-59c991675df8",
      "created_at": "2026-03-05T22:06:02.341Z",
      "content_offset_seconds": 7518,
      "display_name": "MiCkEyRoTtEn",
      "user_badges": [
        {
          "_id": "vip",
          "version": "1"
        },
        {
          "_id": "founder",
          "version": "0"
        },
        {
          "_id": "share-the-love",
          "version": "1"
        }
      ],
      "user_color": "#9ACD32",
      "message": [
        {
          "text": "I'm uh, a teacher of game design at a uni but I never actually graduated, just went directly to work in games for like 9 years so now I gotta quickly graduate to actually keep my teaching job",
          "emoticon": null
        }
      ]
    },
    {
      "id": "96717b07-00c3-42c5-a64a-bc3ec67f6a4c",
      "created_at": "2026-03-05T22:06:07.176Z",
      "content_offset_seconds": 7523,
      "display_name": "MiCkEyRoTtEn",
      "user_badges": [
        {
          "_id": "vip",
          "version": "1"
        },
        {
          "_id": "founder",
          "version": "0"
        },
        {
          "_id": "share-the-love",
          "version": "1"
        }
      ],
      "user_color": "#9ACD32",
      "message": [
        {
          "text": "fun times",
          "emoticon": null
        }
      ]
    },
    {
      "id": "bafe9a26-81d5-4880-8010-2ef94b572225",
      "created_at": "2026-03-05T22:07:31.723Z",
      "content_offset_seconds": 7608,
      "display_name": "MiCkEyRoTtEn",
      "user_badges": [
        {
          "_id": "vip",
          "version": "1"
        },
        {
          "_id": "founder",
          "version": "0"
        },
        {
          "_id": "share-the-love",
          "version": "1"
        }
      ],
      "user_color": "#9ACD32",
      "message": [
        {
          "text": "because rules but yeah I wasn't good at focusing so I dropped out xD",
          "emoticon": null
        }
      ]
    },
    {
      "id": "0a726f94-bfd9-44b9-85cc-cc66010fddab",
      "created_at": "2026-03-05T22:07:55.067Z",
      "content_offset_seconds": 7631,
      "display_name": "MiCkEyRoTtEn",
      "user_badges": [
        {
          "_id": "vip",
          "version": "1"
        },
        {
          "_id": "founder",
          "version": "0"
        },
        {
          "_id": "share-the-love",
          "version": "1"
        }
      ],
      "user_color": "#9ACD32",
      "message": [
        {
          "text": "But now it's mandated since I'm a teacher ugh",
          "emoticon": null
        }
      ]
    },
    {
      "id": "cf27755f-9954-4c42-a7ca-92fd83bf0df9",
      "created_at": "2026-03-05T22:08:10.756Z",
      "content_offset_seconds": 7647,
      "display_name": "MiCkEyRoTtEn",
      "user_badges": [
        {
          "_id": "vip",
          "version": "1"
        },
        {
          "_id": "founder",
          "version": "0"
        },
        {
          "_id": "share-the-love",
          "version": "1"
        }
      ],
      "user_color": "#9ACD32",
      "message": [
        {
          "text": "yeaah",
          "emoticon": null
        }
      ]
    },
    {
      "id": "6bf2958d-0e91-44fb-b6f9-5b8e04580fa6",
      "created_at": "2026-03-05T22:08:31.618Z",
      "content_offset_seconds": 7667,
      "display_name": "MiCkEyRoTtEn",
      "user_badges": [
        {
          "_id": "vip",
          "version": "1"
        },
        {
          "_id": "founder",
          "version": "0"
        },
        {
          "_id": "share-the-love",
          "version": "1"
        }
      ],
      "user_color": "#9ACD32",
      "message": [
        {
          "text": "I dropped out of three different programmes",
          "emoticon": null
        }
      ]
    },
    {
      "id": "e070ac79-2962-4f07-9de9-495782b6730d",
      "created_at": "2026-03-05T22:08:57.252Z",
      "content_offset_seconds": 7693,
      "display_name": "MiCkEyRoTtEn",
      "user_badges": [
        {
          "_id": "vip",
          "version": "1"
        },
        {
          "_id": "founder",
          "version": "0"
        },
        {
          "_id": "share-the-love",
          "version": "1"
        }
      ],
      "user_color": "#9ACD32",
      "message": [
        {
          "text": "Media Engineer, Product Designer and Game Designer",
          "emoticon": null
        }
      ]
    },
    {
      "id": "49aa5afd-864a-43f0-9aa9-e8c05acc9fc1",
      "created_at": "2026-03-05T22:09:22.757Z",
      "content_offset_seconds": 7719,
      "display_name": "MiCkEyRoTtEn",
      "user_badges": [
        {
          "_id": "vip",
          "version": "1"
        },
        {
          "_id": "founder",
          "version": "0"
        },
        {
          "_id": "share-the-love",
          "version": "1"
        }
      ],
      "user_color": "#9ACD32",
      "message": [
        {
          "text": "Finland, filthy socialist country, education is free",
          "emoticon": null
        }
      ]
    },
    {
      "id": "21e4e4e3-65bd-4202-b0e9-e50cecefc4bf",
      "created_at": "2026-03-05T22:09:38.294Z",
      "content_offset_seconds": 7734,
      "display_name": "MiCkEyRoTtEn",
      "user_badges": [
        {
          "_id": "vip",
          "version": "1"
        },
        {
          "_id": "founder",
          "version": "0"
        },
        {
          "_id": "share-the-love",
          "version": "1"
        }
      ],
      "user_color": "#9ACD32",
      "message": [
        {
          "text": "And healthcare v:",
          "emoticon": null
        }
      ]
    },
    {
      "id": "7e56721f-95cd-4548-8aad-9bfae71e0f26",
      "created_at": "2026-03-05T22:10:10.922Z",
      "content_offset_seconds": 7767,
      "display_name": "MiCkEyRoTtEn",
      "user_badges": [
        {
          "_id": "vip",
          "version": "1"
        },
        {
          "_id": "founder",
          "version": "0"
        },
        {
          "_id": "share-the-love",
          "version": "1"
        }
      ],
      "user_color": "#9ACD32",
      "message": [
        {
          "text": "pays to be poor",
          "emoticon": null
        }
      ]
    },
    {
      "id": "55813f87-0988-4d79-bb73-b0827fd9f827",
      "created_at": "2026-03-05T22:11:06.686Z",
      "content_offset_seconds": 7822,
      "display_name": "MiCkEyRoTtEn",
      "user_badges": [
        {
          "_id": "vip",
          "version": "1"
        },
        {
          "_id": "founder",
          "version": "0"
        },
        {
          "_id": "share-the-love",
          "version": "1"
        }
      ],
      "user_color": "#9ACD32",
      "message": [
        {
          "text": "yeah but it's mostly just proving that I already know the contents of each course so I really gotta do very little",
          "emoticon": null
        }
      ]
    },
    {
      "id": "0efb94b4-4fce-4474-b742-91272db97b8a",
      "created_at": "2026-03-05T22:12:21.056Z",
      "content_offset_seconds": 7897,
      "display_name": "MiCkEyRoTtEn",
      "user_badges": [
        {
          "_id": "vip",
          "version": "1"
        },
        {
          "_id": "founder",
          "version": "0"
        },
        {
          "_id": "share-the-love",
          "version": "1"
        }
      ],
      "user_color": "#9ACD32",
      "message": [
        {
          "text": "but the exam was for Swedish which is a mandatory language for Finns cause we're bilingual in theory but in practice no one knows Swedish...",
          "emoticon": null
        }
      ]
    },
    {
      "id": "32c60363-9740-4232-9438-c129f48ea42b",
      "created_at": "2026-03-05T22:12:25.608Z",
      "content_offset_seconds": 7901,
      "display_name": "Fossabot",
      "user_badges": [
        {
          "_id": "moderator",
          "version": "1"
        },
        {
          "_id": "bot-badge",
          "version": "1"
        }
      ],
      "user_color": "#1976D2",
      "message": [
        {
          "text": "waga",
          "emoticon": null
        }
      ]
    },
    {
      "id": "5c4aa70a-03c6-4d46-ac49-5cb4fc208751",
      "created_at": "2026-03-05T22:13:34.876Z",
      "content_offset_seconds": 7971,
      "display_name": "MiCkEyRoTtEn",
      "user_badges": [
        {
          "_id": "vip",
          "version": "1"
        },
        {
          "_id": "founder",
          "version": "0"
        },
        {
          "_id": "share-the-love",
          "version": "1"
        }
      ],
      "user_color": "#9ACD32",
      "message": [
        {
          "text": "yeah V: would love to know Japanese instead of Swedish pff",
          "emoticon": null
        }
      ]
    },
    {
      "id": "096ac401-a285-43c9-b46a-49eabd219bb6",
      "created_at": "2026-03-05T22:14:31.513Z",
      "content_offset_seconds": 8027,
      "display_name": "MiCkEyRoTtEn",
      "user_badges": [
        {
          "_id": "vip",
          "version": "1"
        },
        {
          "_id": "founder",
          "version": "0"
        },
        {
          "_id": "share-the-love",
          "version": "1"
        }
      ],
      "user_color": "#9ACD32",
      "message": [
        {
          "text": "yeah even here working in game industry the language we use is english",
          "emoticon": null
        }
      ]
    },
    {
      "id": "7c79cc83-8ac3-47cd-9302-5a3ac3309f18",
      "created_at": "2026-03-05T22:15:21.717Z",
      "content_offset_seconds": 8078,
      "display_name": "MiCkEyRoTtEn",
      "user_badges": [
        {
          "_id": "vip",
          "version": "1"
        },
        {
          "_id": "founder",
          "version": "0"
        },
        {
          "_id": "share-the-love",
          "version": "1"
        }
      ],
      "user_color": "#9ACD32",
      "message": [
        {
          "text": "it's a dying art",
          "emoticon": null
        }
      ]
    },
    {
      "id": "458cca5f-03ee-4193-a881-b154c05d5aa8",
      "created_at": "2026-03-05T22:15:35.256Z",
      "content_offset_seconds": 8091,
      "display_name": "MiCkEyRoTtEn",
      "user_badges": [
        {
          "_id": "vip",
          "version": "1"
        },
        {
          "_id": "founder",
          "version": "0"
        },
        {
          "_id": "share-the-love",
          "version": "1"
        }
      ],
      "user_color": "#9ACD32",
      "message": [
        {
          "text": "ooh cursive",
          "emoticon": null
        }
      ]
    },
    {
      "id": "753748c5-682c-479e-9679-5780574d21de",
      "created_at": "2026-03-05T22:16:41.732Z",
      "content_offset_seconds": 8158,
      "display_name": "MiCkEyRoTtEn",
      "user_badges": [
        {
          "_id": "vip",
          "version": "1"
        },
        {
          "_id": "founder",
          "version": "0"
        },
        {
          "_id": "share-the-love",
          "version": "1"
        }
      ],
      "user_color": "#9ACD32",
      "message": [
        {
          "text": "here neither",
          "emoticon": null
        }
      ]
    },
    {
      "id": "388a0a15-55fd-4cb8-b67e-fca66d07b2bd",
      "created_at": "2026-03-05T22:17:25.821Z",
      "content_offset_seconds": 8202,
      "display_name": "Fossabot",
      "user_badges": [
        {
          "_id": "moderator",
          "version": "1"
        },
        {
          "_id": "bot-badge",
          "version": "1"
        }
      ],
      "user_color": "#1976D2",
      "message": [
        {
          "text": "Watch vods here! - https://softu.one/",
          "emoticon": null
        }
      ]
    },
    {
      "id": "fdb20fd0-e324-48b6-8a08-3bdd679eb5ff",
      "created_at": "2026-03-05T22:21:26.606Z",
      "content_offset_seconds": 8442,
      "display_name": "Fossabot",
      "user_badges": [
        {
          "_id": "moderator",
          "version": "1"
        },
        {
          "_id": "bot-badge",
          "version": "1"
        }
      ],
      "user_color": "#1976D2",
      "message": [
        {
          "text": "urm",
          "emoticon": null
        }
      ]
    },
    {
      "id": "695faf68-2bbf-48d2-bdf0-c10522aa76c9",
      "created_at": "2026-03-05T22:22:20.318Z",
      "content_offset_seconds": 8496,
      "display_name": "MiCkEyRoTtEn",
      "user_badges": [
        {
          "_id": "vip",
          "version": "1"
        },
        {
          "_id": "founder",
          "version": "0"
        },
        {
          "_id": "share-the-love",
          "version": "1"
        }
      ],
      "user_color": "#9ACD32",
      "message": [
        {
          "text": "dozed off in the middle of writing",
          "emoticon": null
        }
      ]
    },
    {
      "id": "8ae7178b-c691-4371-a231-d91da97dd98d",
      "created_at": "2026-03-05T22:22:35.207Z",
      "content_offset_seconds": 8511,
      "display_name": "MiCkEyRoTtEn",
      "user_badges": [
        {
          "_id": "vip",
          "version": "1"
        },
        {
          "_id": "founder",
          "version": "0"
        },
        {
          "_id": "share-the-love",
          "version": "1"
        }
      ],
      "user_color": "#9ACD32",
      "message": [
        {
          "text": "ugh",
          "emoticon": null
        }
      ]
    },
    {
      "id": "0053fa9d-a2eb-4131-b570-f577ec6d65b3",
      "created_at": "2026-03-05T22:24:07.276Z",
      "content_offset_seconds": 8603,
      "display_name": "MiCkEyRoTtEn",
      "user_badges": [
        {
          "_id": "vip",
          "version": "1"
        },
        {
          "_id": "founder",
          "version": "0"
        },
        {
          "_id": "share-the-love",
          "version": "1"
        }
      ],
      "user_color": "#9ACD32",
      "message": [
        {
          "text": "yeaah I gotta sleepp",
          "emoticon": null
        }
      ]
    },
    {
      "id": "72de0f2e-7e80-437c-ab37-2aa6ab2bf497",
      "created_at": "2026-03-05T22:24:40.044Z",
      "content_offset_seconds": 8636,
      "display_name": "MiCkEyRoTtEn",
      "user_badges": [
        {
          "_id": "vip",
          "version": "1"
        },
        {
          "_id": "founder",
          "version": "0"
        },
        {
          "_id": "share-the-love",
          "version": "1"
        }
      ],
      "user_color": "#9ACD32",
      "message": [
        {
          "text": "have good arts and wiggles",
          "emoticon": null
        }
      ]
    },
    {
      "id": "384d1594-2588-43f8-8117-ddb485a88f09",
      "created_at": "2026-03-05T22:25:21.171Z",
      "content_offset_seconds": 8677,
      "display_name": "Fossabot",
      "user_badges": [
        {
          "_id": "moderator",
          "version": "1"
        },
        {
          "_id": "bot-badge",
          "version": "1"
        }
      ],
      "user_color": "#1976D2",
      "message": [
        {
          "text": "Join the Discord! - https://softu.one/discord",
          "emoticon": null
        }
      ]
    },
    {
      "id": "3818e8a2-e721-4fe0-9332-72392b518075",
      "created_at": "2026-03-05T23:04:26.089Z",
      "content_offset_seconds": 11022,
      "display_name": "Fossabot",
      "user_badges": [
        {
          "_id": "moderator",
          "version": "1"
        },
        {
          "_id": "bot-badge",
          "version": "1"
        }
      ],
      "user_color": "#1976D2",
      "message": [
        {
          "text": "dancin",
          "emoticon": null
        }
      ]
    },
    {
      "id": "d49843bb-26c1-41b3-a5b7-f5c5320a9955",
      "created_at": "2026-03-05T23:15:26.075Z",
      "content_offset_seconds": 11682,
      "display_name": "Fossabot",
      "user_badges": [
        {
          "_id": "moderator",
          "version": "1"
        },
        {
          "_id": "bot-badge",
          "version": "1"
        }
      ],
      "user_color": "#1976D2",
      "message": [
        {
          "text": "Sturdy",
          "emoticon": null
        }
      ]
    },
    {
      "id": "0c52d9d3-339b-4c44-b424-d6a033018d79",
      "created_at": "2026-03-05T23:23:19.013Z",
      "content_offset_seconds": 12155,
      "display_name": "Fossabot",
      "user_badges": [
        {
          "_id": "moderator",
          "version": "1"
        },
        {
          "_id": "bot-badge",
          "version": "1"
        }
      ],
      "user_color": "#1976D2",
      "message": [
        {
          "text": "Explosion nya Explosion",
          "emoticon": null
        }
      ]
    },
    {
      "id": "677a0daa-e3b8-42f0-a323-54f893441187",
      "created_at": "2026-03-05T23:54:39.758Z",
      "content_offset_seconds": 14036,
      "display_name": "Fossabot",
      "user_badges": [
        {
          "_id": "moderator",
          "version": "1"
        },
        {
          "_id": "bot-badge",
          "version": "1"
        }
      ],
      "user_color": "#1976D2",
      "message": [
        {
          "text": "adeyrj, thank you for following!",
          "emoticon": null
        }
      ]
    },
    {
      "id": "c69dc5fa-1b56-4d5e-8080-431c21a5812a",
      "created_at": "2026-03-05T23:54:43.099Z",
      "content_offset_seconds": 14039,
      "display_name": "adeyrj",
      "user_badges": [],
      "user_color": null,
      "message": [
        {
          "text": "love your vibes add me on dis-cord so that we can play together & join and your next stream  username :eriksmith_4",
          "emoticon": null
        }
      ]
    },
    {
      "id": "92a39525-c252-4476-9345-b45e0e74b573",
      "created_at": "2026-03-06T00:14:21.085Z",
      "content_offset_seconds": 15217,
      "display_name": "Fossabot",
      "user_badges": [
        {
          "_id": "moderator",
          "version": "1"
        },
        {
          "_id": "bot-badge",
          "version": "1"
        }
      ],
      "user_color": "#1976D2",
      "message": [
        {
          "text": "waga",
          "emoticon": null
        }
      ]
    }
  ]
}
